MANIFEST.in
README
setup.py
jaobi/__init__.py
jaobi/cache.py
jaobi/fields.py
jaobi/models.py
jaobi/myzmq.py
jaobi/scheduler.py
jaobi/utils.py
jaobi/web.py
jaobi.egg-info/PKG-INFO
jaobi.egg-info/SOURCES.txt
jaobi.egg-info/dependency_links.txt
jaobi.egg-info/pbr.json
jaobi.egg-info/requires.txt
jaobi.egg-info/top_level.txt
jaobi/commands/__init__.py
jaobi/commands/startbe.py
jaobi/reports/__init__.py
jaobi/reports/exceptions.py
jaobi/reports/realtime.py
jaobi/reports/reduced.py
jaobi/static/jaobi/js/interphone.js
jaobi/static/jaobi/js/jaobi.js
jaobi/static/jaobi/js/utils.js
jaobi/templates/consumer_server.html