Metadata-Version: 1.1
Name: jaobi
Version: 0.14.11.1
Summary: jaobi is really cool software
Home-page: https://some-url-to-my-project.com
Author: You Buddy
Author-email: you@somewhere.com
License: UNKNOWN
Platform: UNKNOWN
Classifier: Development Status :: 3 - Alpha
Classifier: Programming Language :: Python :: 3
Provides: jaobi
